funkmodel/__init__.py
funkmodel/father_model.py
funkmodel/funkmodel.py
funkmodel/precision_model.py
funkmodel/simple_math.py
funkmodel/string_model.py
funkmodel/time_model.py
funkmodel/wallet_model.py
funkmodel-0.1.1.dist-info/METADATA
funkmodel-0.1.1.dist-info/WHEEL
funkmodel-0.1.1.dist-info/top_level.txt
funkmodel-0.1.1.dist-info/RECORD
