Metadata-Version: 2.1
Name: funkmodel
Version: 0.1.1
Summary: Pre Built Functionality for Tortoise Class Models Inheritance
Home-page: https://github.com/funkaclau
Author: funkaclau
Author-email: UNKNOWN
License: UNKNOWN
Platform: UNKNOWN
Requires-Dist: tortoise-orm
